<?xml version="1.0" encoding="UTF-8"?>
<cms-blocks xmlns:xsi="http://www.w3.org/2001/XMLSchema-instance"
            xsi:noNamespaceSchemaLocation="https://raw.githubusercontent.com/shopware/platform/trunk/src/Core/Content/Cms/Schema/cms-block-1.0.xsd">
    <!-- Platzhalter-Block, der auf Custom Fields verweist. Projektteams fügen hier ein eigenes CMS-Element hinzu. -->
    <cms-block name="acme-custom-field-hint"
               category="text"
               label="Acme Hinweis (Custom Field)">
        <slots>
            <slot type="text"
                  slot="content">
                <config>
                    <!-- Shopware bietet über `mapped` Zugriff auf Custom Fields des Produktes. -->
                    <content source="mapped">customFields.acme_badge_text</content>
                </config>
            </slot>
        </slots>
    </cms-block>
</cms-blocks>
